failwin_my_project/__init__.py
failwin_my_project/consts.py
failwin_my_project/utils.py
failwin_my_project/my_package/__init__.py
failwin_my_project/my_package/my_mod_1.py
failwin_my_project/my_package/my_mod_2.py
failwin_my_project/my_package/my_folder/__init__.py
failwin_my_project/my_package/my_folder/my_folder_mod_1.py
failwin_my_project-0.0.5.dist-info/METADATA
failwin_my_project-0.0.5.dist-info/WHEEL
failwin_my_project-0.0.5.dist-info/licenses/LICENSE
failwin_my_project-0.0.5.dist-info/RECORD
